qrbill/__init__.py
qrbill/bill.py
qrbill-1.2.0.dist-info/licenses/LICENSE.TXT
qrbill-1.2.0.dist-info/METADATA
qrbill-1.2.0.dist-info/WHEEL
qrbill-1.2.0.dist-info/entry_points.txt
qrbill-1.2.0.dist-info/top_level.txt
qrbill-1.2.0.dist-info/RECORD
