Metadata-Version: 2.4
Name: qrbill
Version: 1.2.0
Summary: A library to generate Swiss QR-bill payment slips.
Author-email: Claude Paroz <claude@2xlibre.net>
License-Expression: MIT
Project-URL: Homepage, https://github.com/claudep/swiss-qr-bill/
Project-URL: Changelog, https://github.com/claudep/swiss-qr-bill/CHANGELOG.rst
Classifier: Development Status :: 5 - Production/Stable
Classifier: Programming Language :: Python :: 3
Requires-Python: >=3.9
License-File: LICENSE.TXT
Requires-Dist: iso3166
Requires-Dist: python-stdnum>=1.13
Requires-Dist: qrcode
Requires-Dist: svgwrite
Dynamic: license-file
